pysophia2/__init__.py
pysophia2/db.py
pysophia2/ngram.py
pysophia2/tools.py
sophia2/__init__.py
sophia2/db.py
sophia2/tools.py
pytetete-0.0.45.dist-info/LICENSE
pytetete-0.0.45.dist-info/METADATA
pytetete-0.0.45.dist-info/WHEEL
pytetete-0.0.45.dist-info/top_level.txt
pytetete-0.0.45.dist-info/RECORD
