Metadata-Version: 2.1
Name: pytetete
Version: 0.0.45
Summary: Python library for news discourse analysis
Home-page: https://github.com/TeamSophia2/pySophia2
Author: Team Sophia2
Author-email: mvernier@inf.uach.cl
License: MIT
Platform: UNKNOWN
Classifier: Programming Language :: Python :: 3
Classifier: Programming Language :: Python :: 3.8
Requires-Dist: pandas
Requires-Dist: mariadb
Requires-Dist: elasticsearch
Requires-Dist: spacy
Requires-Dist: matplotlib
Requires-Dist: numpy
